<?xml version="1.0" encoding="utf-8" ?>
<dwsync>
<file name="_documentation.html" server="uofmballroom.com" local="128962548000000000" remote="128962548000000000" />
<file name="fckeditor.js" server="uofmballroom.com" local="128962548000000000" remote="128962548000000000" />
<file name="fckeditor.asp" server="uofmballroom.com" local="128962548000000000" remote="128962548000000000" />
<file name="fckeditor.cfm" server="uofmballroom.com" local="128962548000000000" remote="128962548000000000" />
<file name="fckutils.cfm" server="uofmballroom.com" local="128962548000000000" remote="128962548000000000" />
<file name="_upgrade.html" server="uofmballroom.com" local="128962548000000000" remote="128962548000000000" />
<file name="_whatsnew.html" server="uofmballroom.com" local="128962548000000000" remote="128962548000000000" />
<file name="_whatsnew_history.html" server="uofmballroom.com" local="128962548000000000" remote="128962548000000000" />
<file name="fckconfig.js" server="uofmballroom.com" local="129070548000000000" remote="129070548000000000" />
<file name="fckeditor.afp" server="uofmballroom.com" local="128962548000000000" remote="128962548000000000" />
<file name="fckeditor.cfc" server="uofmballroom.com" local="128962548000000000" remote="128962548000000000" />
<file name="fckeditor.lasso" server="uofmballroom.com" local="128962548000000000" remote="128962548000000000" />
<file name="fckeditor.php" server="uofmballroom.com" local="128962548000000000" remote="128962548000000000" />
<file name="fckeditor.pl" server="uofmballroom.com" local="128962548000000000" remote="128962548000000000" />
<file name="fckeditor.py" server="uofmballroom.com" local="128962548000000000" remote="128962548000000000" />
<file name="fckeditor_php4.php" server="uofmballroom.com" local="128962548000000000" remote="128962548000000000" />
<file name="fckeditor_php5.php" server="uofmballroom.com" local="128962548000000000" remote="128962548000000000" />
<file name="fckpackager.xml" server="uofmballroom.com" local="128962548000000000" remote="128962548000000000" />
<file name="fckstyles.xml" server="uofmballroom.com" local="128962548000000000" remote="128962548000000000" />
<file name="fcktemplates.xml" server="uofmballroom.com" local="128962548000000000" remote="128962548000000000" />
<file name="license.txt" server="uofmballroom.com" local="128962548000000000" remote="128962548000000000" />
</dwsync>